{
  "name": "Susceptibility To Divine Power",
  "type": "flaw",
  "img": "systems/arm5e/assets/icons/VF/hermetic.svg",
  "effects": [],
  "flags": {
    "core": {},
    "cf": {
      "id": "temp_zctzc5h7p5",
      "path": "Flaws#/CF_SEP/Hermetic",
      "color": "#000000"
    }
  },
  "system": {
    "description": "You are especially sensitive to the Dominion and suffer twice the normal penalties (such as spellcasting modifiers and botch rolls) to your magic when in a divine aura.",
    "source": "ArM5",
    "page": 59,
    "type": "hermetic",
    "impact": {
      "value": "minor"
    },
    "indexKey": "susceptibility-to-divine-power"
  },
  "_stats": {
    "systemId": "arm5e",
    "systemVersion": "2.2.2.15",
    "coreVersion": "11.311",
    "createdTime": 1662235751538,
    "modifiedTime": 1696141994827,
    "lastModifiedBy": "1JBSgWiiwizu7vru"
  },
  "folder": "8FTSMAxaThguRoxc",
  "_id": "LcOGbLOqbYp02y6Y",
  "sort": 0,
  "ownership": {
    "default": 0,
    "1JBSgWiiwizu7vru": 3
  },
  "_key": "!items!LcOGbLOqbYp02y6Y"
}