{
  "name": "Skilled Parens",
  "type": "virtue",
  "img": "systems/arm5e/assets/icons/VF/hermetic.svg",
  "effects": [],
  "flags": {
    "core": {},
    "cf": {
      "id": "temp_nxctmjlqqdb",
      "path": "Virtues#/CF_SEP/Hermetic",
      "color": "#000000"
    }
  },
  "system": {
    "source": "ArM5",
    "page": 48,
    "type": "hermetic",
    "impact": {
      "value": "minor"
    },
    "indexKey": "skilled-parens",
    "description": "Your parens was more powerful, and a better teacher, than is common. You gain an additional 60 experience points and 30 spell levels during apprenticeship. This Virtue has no effect on your study after apprenticeship, but you still have a close relationship with a powerful magus."
  },
  "_stats": {
    "systemId": "arm5e",
    "systemVersion": "2.2.2.15",
    "coreVersion": "11.311",
    "createdTime": 1662235751354,
    "modifiedTime": 1696141995847,
    "lastModifiedBy": "1JBSgWiiwizu7vru"
  },
  "folder": "C8jqPqfblXk6hGCE",
  "_id": "GllC6922LmZGurtr",
  "sort": 0,
  "ownership": {
    "default": 0,
    "1JBSgWiiwizu7vru": 3
  },
  "_key": "!items!GllC6922LmZGurtr"
}